LAB3/EC4/Ecuacion4.v
//Francisco Montúfar #19379
//Archivo de la POS de la tabla 2

module Ecuacion4(); //se crea el módulo

reg A;
reg B;
reg C; //Se crean las variables de entrada, en este caso A, B y C

wire sal1;
wire sal2;
wire sal3; // variables de las salidas, en este caso son las salidas de los NOT
wire sal4;
wire sal5;
wire sal6;
wire sal7;
wire sal8; //variables de salida de los OR
wire Y; //variable de salida del AND


not s0(sal1,A);
not s1(sal2,B); //comandos para realizar la operacion de la compuerta
not s2(sal3,C); //en este caso son NOT, la estructura es [Compuerta nombre(salida,entrada(s))]

or s3(sal4, A, B, C);
or s4(sal5, A, sal2, C);
or s5(sal6, A, sal2, sal3);
or s6(sal7, sal1, B, C);   //comandos para realizar operacion de compuerta
or s7(sal8, sal1, B, sal3);//en este caso son OR 

and s8(Y, sal4, sal5, sal6, sal7, sal8); //comando para el AND, ojo: se usan de entradas las salidas de los anteriores


// iniciar operaciones
initial begin

  $display("A B C | Y"); // se agrega un formato para facilitar comprension
  $display("------------");

  $monitor("%b %b %b | %b", A, B, C, Y); //monitorea las variables con el formato dado
  A = 0; B = 0; C = 0;  //condiciones iniciales de las entradas
  #1 C = 1;
  #1 B = 1; C = 0;
  #1 C = 1;
  #1 A = 1; B = 0; C = 0;  // se van cambiando los valores depende a la tabla
  #1 C = 1;
  #1 B = 1; C = 0;
  #1 C = 1;
  #1 $finish;
end


//habilitar GTKWave
  initial
      begin
          $dumpfile("Ecuacion4_tb.vcd");
          $dumpvars (0, Ecuacion4);
      end
endmodule

LAB3/EC4/Ecuacion4_tb.vcd
$date
	Sun Aug 02 12:49:40 2020
$end
$version
	Icarus Verilog
$end
$timescale
	1ps
$end
$scope module Ecuacion4 $end
$var wire 1 ! Y $end
$var wire 1 " sal1 $end
$var wire 1 # sal2 $end
$var wire 1 $ sal3 $end
$var wire 1 % sal4 $end
$var wire 1 & sal5 $end
$var wire 1 ' sal6 $end
$var wire 1 ( sal7 $end
$var wire 1 ) sal8 $end
$var reg 1 * A $end
$var reg 1 + B $end
$var reg 1 , C $end
$upscope $end
$enddefinitions $end
#0
$dumpvars
0,
0+
0*
1)
1(
1'
1&
0%
1$
1#
1"
0!
$end
#1
1!
1%
0$
1,
#2
0!
0&
1$
0#
0,
1+
#3
0'
1&
0$
1,
#4
1$
1)
0(
1#
1'
0"
0,
0+
1*
#5
0)
1(
0$
1,
#6
1!
1$
1)
0#
0,
1+
#7
0$
1,
