LAB8/Ej1/Ejercicio_1.v
//Contador de 12 bits

module cont(input wire clk, EN, reset, LDEN, input wire [11:0]LD, output reg[11:0]Q);

always@(posedge clk or posedge reset or posedge LDEN)begin

if(reset)
  Q <= 12'b000000000000; //si se activa el reset, todos los bits en 0

  else if (LDEN)
  Q <= LD;                //si se activa el load, se precarga un valor

  else if (EN)  //si se activa el enabled cuenta
  Q <= Q + 12'b1;
   end

endmodule

LAB8/Ej1/Ejercicio1_tb.v
//testbench

module testbench();
reg clk, reset, EN, LDEN;
reg [11:0]LD; //input contador
wire [11:0]Q; //salidas

cont  u1 (clk, EN, reset, LDEN, LD, Q);

always
#1 clk  = ~clk;

initial begin
#1
$display(" Selector ");
$display ("CLK EN RST LDEN LD| Q");
$display("-----------------------------|------------");
$monitor(" %b %b %b %b %b  |  %b ",clk, EN, reset, LDEN, LD, Q);
    clk = 0; reset = 0; EN = 0; LDEN = 0; LD = 0;
    #1 reset = 1;
    #1 reset = 0;
    #1 reset = 0;
    #1 EN = 1;
    #10 reset = 0;
    #10 reset = 0;
    #1 reset = 1; EN = 0;
    #1 reset = 0;
    #5 LDEN = 1; LD = 12'b111110000000;
    #1 EN = 1; LDEN = 0;


  end

  initial
    #145 $finish;

  initial begin
    $dumpfile("Ejercicio1_tb.vcd");
    $dumpvars(0, testbench);

  end
  endmodule

LAB8/Ej1/Ejercicio1_tb.vcd
$date
	Fri Oct 23 21:24:41 2020
$end
$version
	Icarus Verilog
$end
$timescale
	1ps
$end
$scope module testbench $end
$var wire 12 ! Q [11:0] $end
$var reg 1 " EN $end
$var reg 12 # LD [11:0] $end
$var reg 1 $ LDEN $end
$var reg 1 % clk $end
$var reg 1 & reset $end
$scope module u1 $end
$var wire 1 " EN $end
$var wire 12 ' LD [11:0] $end
$var wire 1 $ LDEN $end
$var wire 1 % clk $end
$var wire 1 & reset $end
$var reg 12 ( Q [11:0] $end
$upscope $end
$upscope $end
$enddefinitions $end
#0
$dumpvars
bx (
bx '
x&
x%
x$
bx #
x"
bx !
$end
#1
b0 #
b0 '
0$
0"
0&
0%
#2
b0 !
b0 (
1&
1%
#3
0&
0%
#4
1%
#5
1"
0%
#6
b1 !
b1 (
1%
#7
0%
#8
b10 !
b10 (
1%
#9
0%
#10
b11 !
b11 (
1%
#11
0%
#12
b100 !
b100 (
1%
#13
0%
#14
b101 !
b101 (
1%
#15
0%
#16
b110 !
b110 (
1%
#17
0%
#18
b111 !
b111 (
1%
#19
0%
#20
b1000 !
b1000 (
1%
#21
0%
#22
b1001 !
b1001 (
1%
#23
0%
#24
b1010 !
b1010 (
1%
#25
0%
#26
b0 !
b0 (
1%
0"
1&
#27
0%
0&
#28
1%
#29
0%
#30
1%
#31
0%
#32
b111110000000 !
b111110000000 (
1%
b111110000000 #
b111110000000 '
1$
#33
0%
0$
1"
#34
b111110000001 !
b111110000001 (
1%
#35
0%
#36
b111110000010 !
b111110000010 (
1%
#37
0%
#38
b111110000011 !
b111110000011 (
1%
#39
0%
#40
b111110000100 !
b111110000100 (
1%
#41
0%
#42
b111110000101 !
b111110000101 (
1%
#43
0%
#44
b111110000110 !
b111110000110 (
1%
#45
0%
#46
b111110000111 !
b111110000111 (
1%
#47
0%
#48
b111110001000 !
b111110001000 (
1%
#49
0%
#50
b111110001001 !
b111110001001 (
1%
#51
0%
#52
b111110001010 !
b111110001010 (
1%
#53
0%
#54
b111110001011 !
b111110001011 (
1%
#55
0%
#56
b111110001100 !
b111110001100 (
1%
#57
0%
#58
b111110001101 !
b111110001101 (
1%
#59
0%
#60
b111110001110 !
b111110001110 (
1%
#61
0%
#62
b111110001111 !
b111110001111 (
1%
#63
0%
#64
b111110010000 !
b111110010000 (
1%
#65
0%
#66
b111110010001 !
b111110010001 (
1%
#67
0%
#68
b111110010010 !
b111110010010 (
1%
#69
0%
#70
b111110010011 !
b111110010011 (
1%
#71
0%
#72
b111110010100 !
b111110010100 (
1%
#73
0%
#74
b111110010101 !
b111110010101 (
1%
#75
0%
#76
b111110010110 !
b111110010110 (
1%
#77
0%
#78
b111110010111 !
b111110010111 (
1%
#79
0%
#80
b111110011000 !
b111110011000 (
1%
#81
0%
#82
b111110011001 !
b111110011001 (
1%
#83
0%
#84
b111110011010 !
b111110011010 (
1%
#85
0%
#86
b111110011011 !
b111110011011 (
1%
#87
0%
#88
b111110011100 !
b111110011100 (
1%
#89
0%
#90
b111110011101 !
b111110011101 (
1%
#91
0%
#92
b111110011110 !
b111110011110 (
1%
#93
0%
#94
b111110011111 !
b111110011111 (
1%
#95
0%
#96
b111110100000 !
b111110100000 (
1%
#97
0%
#98
b111110100001 !
b111110100001 (
1%
#99
0%
#100
b111110100010 !
b111110100010 (
1%
#101
0%
#102
b111110100011 !
b111110100011 (
1%
#103
0%
#104
b111110100100 !
b111110100100 (
1%
#105
0%
#106
b111110100101 !
b111110100101 (
1%
#107
0%
#108
b111110100110 !
b111110100110 (
1%
#109
0%
#110
b111110100111 !
b111110100111 (
1%
#111
0%
#112
b111110101000 !
b111110101000 (
1%
#113
0%
#114
b111110101001 !
b111110101001 (
1%
#115
0%
#116
b111110101010 !
b111110101010 (
1%
#117
0%
#118
b111110101011 !
b111110101011 (
1%
#119
0%
#120
b111110101100 !
b111110101100 (
1%
#121
0%
#122
b111110101101 !
b111110101101 (
1%
#123
0%
#124
b111110101110 !
b111110101110 (
1%
#125
0%
#126
b111110101111 !
b111110101111 (
1%
#127
0%
#128
b111110110000 !
b111110110000 (
1%
#129
0%
#130
b111110110001 !
b111110110001 (
1%
#131
0%
#132
b111110110010 !
b111110110010 (
1%
#133
0%
#134
b111110110011 !
b111110110011 (
1%
#135
0%
#136
b111110110100 !
b111110110100 (
1%
#137
0%
#138
b111110110101 !
b111110110101 (
1%
#139
0%
#140
b111110110110 !
b111110110110 (
1%
#141
0%
#142
b111110110111 !
b111110110111 (
1%
#143
0%
#144
b111110111000 !
b111110111000 (
1%
