LAB8/Ej3/Ejercicio_3.v
//ALU

module  ALU(input wire [3:0]A, input wire [3:0]B, input wire [2:0]Selector, output reg[3:0]Out);


always @(*)
  begin
  case (Selector)
  3'b000: Out = A & B;
  3'b001: Out = A | B;
  3'b010: Out = A + B;
  3'b100: Out = A & ~B;
  3'b101: Out = A | ~B;
  3'b110: Out = A - B;
  3'b111: Out = (A < B) ? 1:0;
  default: Out = A | B;
endcase

end
endmodule

LAB8/Ej3/Ejercicio3_tb.v
module testbench();

reg [3:0]A; //input
reg [3:0]B;
reg [2:0]Selector; //selector
wire [3:0]Out;     //salidas

ALU  u1 (A, B, Selector, Out);



initial begin
$display ("\n");
$display(" ALU ");
$display ("A    |    B   |  SEL   |   Out");
$display("---------|------------");
$monitor(" %b | %b  | %b | %b ", A, B, Selector, Out);
#1 A = 4'b0000; B = 4'b0000; Selector = 3'b000;
#1 A = 4'b0011; B = 4'b0100; Selector = 3'b000;
#1 A = 4'b0010; B = 4'b1000; Selector = 3'b001;
#1 A = 4'b0011; B = 4'b0010; Selector = 3'b010;
#1 A = 4'b0110; B = 4'b1010; Selector = 3'b100;
#1 A = 4'b0110; B = 4'b1100; Selector = 3'b101;
#1 A = 4'b1010; B = 4'b1001; Selector = 3'b110;
#1 A = 4'b1110; B = 4'b0110; Selector = 3'b111;




  end

  initial
    #145 $finish;

  initial begin
    $dumpfile("Ejercicio3_tb.vcd");
    $dumpvars(0, testbench);

  end
  endmodule

LAB8/Ej3/Ejercicio3_tb.vcd
$date
	Sat Oct 24 19:46:12 2020
$end
$version
	Icarus Verilog
$end
$timescale
	1ps
$end
$scope module testbench $end
$var wire 4 ! Out [3:0] $end
$var reg 4 " A [3:0] $end
$var reg 4 # B [3:0] $end
$var reg 3 $ Selector [2:0] $end
$scope module u1 $end
$var wire 4 % A [3:0] $end
$var wire 4 & B [3:0] $end
$var wire 3 ' Selector [2:0] $end
$var reg 4 ( Out [3:0] $end
$upscope $end
$upscope $end
$enddefinitions $end
#0
$dumpvars
bx (
bx '
bx &
bx %
bx $
bx #
bx "
bx !
$end
#1
b0 !
b0 (
b0 $
b0 '
b0 #
b0 &
b0 "
b0 %
#2
b100 #
b100 &
b11 "
b11 %
#3
b1010 !
b1010 (
b1 $
b1 '
b1000 #
b1000 &
b10 "
b10 %
#4
b101 !
b101 (
b10 $
b10 '
b10 #
b10 &
b11 "
b11 %
#5
b100 !
b100 (
b100 $
b100 '
b1010 #
b1010 &
b110 "
b110 %
#6
b111 !
b111 (
b101 $
b101 '
b1100 #
b1100 &
#7
b1 !
b1 (
b110 $
b110 '
b1001 #
b1001 &
b1010 "
b1010 %
#8
b0 !
b0 (
b111 $
b111 '
b110 #
b110 &
b1110 "
b1110 %
