LAB9/Ej4/Ejercicio_4.v
module BUFFTRI(input wire EN, input wire [3:0]A, output wire [3:0]out);
assign out = EN ? A:4'bz;
endmodule

LAB9/Ej4/Ejercicio4_tb.v
module testbench();
  reg EN;
  reg [3:0]A;
  wire [3:0]out;


BUFFTRI a1(EN, A, out);




initial begin

$display(" ejercicio 4");
$display ("EN  A | OUT ");
$display("-------|------------");
$monitor("%b %b  | %b", EN, A, out);
      EN = 0; A[3] = 0;  A[2] = 0;  A[1] = 0;  A[0] = 0;
   #1 EN = 1; A[3] = 1;  A[2] = 1;  A[1] = 0;  A[0] = 1;
   #1 EN = 0; A[3] = 1;  A[2] = 1;  A[1] = 0;  A[0] = 1;
   #1 EN = 1; A[3] = 1;  A[2] = 0;  A[1] = 1;  A[0] = 1;
   #1 EN = 0; A[3] = 1;  A[2] = 0;  A[1] = 1;  A[0] = 1;
   #1 EN = 1; A[3] = 1;  A[2] = 1;  A[1] = 1;  A[0] = 1;
   #1 EN = 0; A[3] = 1;  A[2] = 1;  A[1] = 1;  A[0] = 1;
   #1 EN = 1; A[3] = 0;  A[2] = 1;  A[1] = 0;  A[0] = 0;
   #1 EN = 0; A[3] = 0;  A[2] = 1;  A[1] = 0;  A[0] = 0;


end

initial
  #9 $finish;

  initial begin
  $dumpfile("Ejercicio4_tb.vcd");
  $dumpvars(0, testbench);
end
endmodule

LAB9/Ej4/Ejercicio4_tb.vcd
$date
	Sat Oct 31 03:42:21 2020
$end
$version
	Icarus Verilog
$end
$timescale
	1ps
$end
$scope module testbench $end
$var wire 4 ! out [3:0] $end
$var reg 4 " A [3:0] $end
$var reg 1 # EN $end
$scope module a1 $end
$var wire 4 $ A [3:0] $end
$var wire 1 # EN $end
$var wire 4 % out [3:0] $end
$upscope $end
$upscope $end
$enddefinitions $end
#0
$dumpvars
bz %
b0 $
0#
b0 "
bz !
$end
#1
b1101 !
b1101 %
b1101 "
b1101 $
1#
#2
bz !
bz %
0#
#3
b1011 !
b1011 %
b1011 "
b1011 $
1#
#4
bz !
bz %
0#
#5
b1111 !
b1111 %
b1111 "
b1111 $
1#
#6
bz !
bz %
0#
#7
b100 !
b100 %
b100 "
b100 $
1#
#8
bz !
bz %
0#
