LAB5/Lab5.v
//LAB 5
//FRANCISCO MONTÚFAR 19379


//mux2:1
module mux2a1(input wire  d0, d1,  //mux2:1 (entradas)
                    input wire s, //entrada (selector)
                  output wire y); //salida

assign y = s ? d1 : d0;

endmodule


//mux4:1 implementado con un 2:1
module mux4a1(input wire d0, d1, d2, d3,
                      input wire s0, s1,
                         output wire y);

wire l1,h1 ;

mux2a1  lowmux(d0, d1, s0, l1);
mux2a1  highmux(d2, d3, s0, h1);
mux2a1  outmux(l1, h1, s1, y);

endmodule


//mux8:1 implementado con 4:1

module mux8a1(input wire d0, d1, d2, d3, d4, d5, d6, d7,
                                   input wire s, s1, s2,
                                         output wire y);
wire sal1, sal2;

mux4a1  fun1(d0, d1, d2, d3, s, s1, sal1);
mux4a1  fun2(d4, d5, d6, d7, s, s1, sal2);
mux2a1  fun3(sal1, sal2, s2, y);

endmodule


//tabla 01 con multiplexores

//tabla 01 con mux8:1

module t1mux8a1(input wire A, B, C, output wire Y);

wire l, h;

assign l = 0;
assign h = 1;


mux8a1 fun1(l, h, h, l, h, l, l, h, C, B, A, Y);

endmodule

//tabla 01 con mux4:1

module t1mux4a1(input wire A, B, C, output wire y);

mux4a1 f1(C, ~C, ~C, C, B, A, y);

endmodule

//tabla 01 con mux2:1

module t1mux2a1(input wire A, B, C, output wire y);

mux2a1 c1(B^C, B~^C, A, y);

endmodule

// tabla 02 con multiplexores

//tabla 02 con mux8:1

module t2mux8a1(input wire A, B, C, output wire y);

wire l, h;

assign l = 0;
assign h = 1;

mux8a1 fun2(h, h, l, l, h, h, h, l, C, B, A, y);

endmodule

// tabla 02 con mux4:1

module t2mux4a1(input wire A, B, C, output wire y);

wire l;
assign l = 0;

mux4a1 f2(~C, l, C, ~C, B, A, y);

endmodule

//tabla 02 con mux 2:1

module t2mux2a1(input wire A, B, C, output wire y);

mux2a1 b2(B~|C, B~&C, A, y);

endmodule

LAB5-master/Lab5_tb.v
//Francisco Montúfar
//carnet 19379


module testbench();
reg a1, a2, a3; // entradas mux8:1 tabla1
reg a4, a5, a6; //entradas mux4:1 tabla1
reg a7, a8, a9;// entradas mux2:1 tabla1

reg b1, b2, b3;// entradas mux8:1 tabla2
reg b4, b5, b6; //entradas mux 4:1 tabla2
reg b7, b8, b9; // entrads mux 2:1 tabla2

wire s1, s2, s3, s4, s5, s6; //salidas

//mux tabla 1

t1mux8a1  m81(a1, a2, a3, s1);
t1mux4a1  m41(a4, a5, a6, s2);
t1mux2a1  m21(a7, a8, a9, s3);

t2mux8a1  x81(b1, b2, b3, s4);
t2mux4a1  x41(b4, b5, b6, s5);
t2mux2a1  x21(b7, b8, b9, s6);


initial begin //mux 8:1 tabla1

$display("Tabla 1, mux 8:1");
$display("A B C | Y");
$display("------|---");
$monitor("%b %b %b | %b", a1, a2, a3, s1);
  a1 = 0; a2 = 0; a3 = 0;
#1 a1 = 0; a2 = 0; a3 = 1;
#1 a1 = 0; a2 = 1; a3 = 0;
#1 a1 = 0; a2 = 1; a3 = 1;
#1 a1 = 1; a2 = 0; a3 = 0;
#1 a1 = 1; a2 = 0; a3 = 1;
#1 a1 = 1; a2 = 1; a3 = 0;
#1 a1 = 1; a2 = 1; a3 = 1;
end //Termina en 8


initial begin//mux 4:1 tabla 1

    #9
    $display("\n");
    $display("Tabla 1, mux 4:1");
    $display("A B C | Y");
    $display("--------|---");
    $monitor("%b %b %b  | %b", a4, a5, a6, s2);
      a4 = 0; a5 = 0; a6 = 0;
    #1 a4 = 0; a5 = 0; a6 = 1;
    #1 a4 = 0; a5 = 1; a6 = 0;
    #1 a4 = 0; a5 = 1; a6 = 1;
    #1 a4 = 1; a5 = 0; a6 = 0;
    #1 a4 = 1; a5 = 0; a6 = 1;
    #1 a4 = 1; a5 = 1; a6 = 0;
    #1 a4 = 1; a5 = 1; a6 = 1;
end //Termina en 16


initial begin//mux2:1 tabla1

    #17
    $display("\n");
    $display("Tabla 1, mux2:1");
    $display("A B C | Y");
    $display("--------|---");
    $monitor("%b %b %b  | %b", a7, a8, a9, s3);
      a7 = 0; a8 = 0; a9 = 0;
    #1 a7 = 0; a8 = 0; a9 = 1;
    #1 a7 = 0; a8 = 1; a9 = 0;
    #1 a7 = 0; a8 = 1; a9 = 1;
    #1 a7 = 1; a8 = 0; a9 = 0;
    #1 a7 = 1; a8 = 0; a9 = 1;
    #1 a7 = 1; a8 = 1; a9 = 0;
    #1 a7 = 1; a8 = 1; a9 = 1;
end //Termina en 24



initial begin //mux8:1 tabla2
  #25
  $display("\n");
  $display("Tabla 2, mux8:1");
  $display("A B C | Y");
  $display("--------|---");
  $monitor("%b %b %b | %b", b1, b2, b3, s4);
    b1 = 0; b2 = 0; b3 = 0;
  #1 b1 = 0; b2 = 0; b3 = 1;
  #1 b1 = 0; b2 = 1; b3 = 0;
  #1 b1 = 0; b2 = 1; b3 = 1;
  #1 b1 = 1; b2 = 0; b3 = 0;
  #1 b1 = 1; b2 = 0; b3 = 1;
  #1 b1 = 1; b2 = 1; b3 = 0;
  #1 b1 = 1; b2 = 1; b3 = 1;

end//termina en 32

initial begin //mux4:1 tabla 2
  #33
  $display("\n");
  $display("Tabla 2, mux4:1");
  $display("A B C | Y");
  $display("--------|---");
  $monitor("%b %b %b | %b", b4, b5, b6, s5);
    b4 = 0; b5 = 0; b6 = 0;
  #1 b4 = 0; b5 = 0; b6 = 1;
  #1 b4 = 0; b5 = 1; b6 = 0;
  #1 b4 = 0; b5 = 1; b6 = 1;
  #1 b4 = 1; b5 = 0; b6 = 0;
  #1 b4 = 1; b5 = 0; b6 = 1;
  #1 b4 = 1; b5 = 1; b6 = 0;
  #1 b4 = 1; b5 = 1; b6 = 1;

end//termina en 40

initial begin //tabla 6
  #41
  $display("\n");
  $display("Tabla 2, mux2:1");
  $display("A B C | Y");
  $display("--------|---");
  $monitor("%b %b %b | %b", b7, b8, b9, s6);
    b7 = 0; b8 = 0; b9 = 0;
  #1 b7 = 0; b8 = 0; b9 = 1;
  #1 b7 = 0; b8 = 1; b9 = 0;
  #1 b7 = 0; b8 = 1; b9 = 1;
  #1 b7 = 1; b8 = 0; b9 = 0;
  #1 b7 = 1; b8 = 0; b9 = 1;
  #1 b7 = 1; b8 = 1; b9 = 0;
  #1 b7 = 1; b8 = 1; b9 = 1;

end//termina en 48

initial
        #49 $finish;

    initial begin
        $dumpfile("lab5_tb.vcd");
        $dumpvars(0, testbench);
    end
endmodule

LAB5/lab5_tb.vcd
$date
	Sun Aug 16 00:06:47 2020
$end
$version
	Icarus Verilog
$end
$timescale
	1ps
$end
$scope module testbench $end
$var wire 1 ! s6 $end
$var wire 1 " s5 $end
$var wire 1 # s4 $end
$var wire 1 $ s3 $end
$var wire 1 % s2 $end
$var wire 1 & s1 $end
$var reg 1 ' a1 $end
$var reg 1 ( a2 $end
$var reg 1 ) a3 $end
$var reg 1 * a4 $end
$var reg 1 + a5 $end
$var reg 1 , a6 $end
$var reg 1 - a7 $end
$var reg 1 . a8 $end
$var reg 1 / a9 $end
$var reg 1 0 b1 $end
$var reg 1 1 b2 $end
$var reg 1 2 b3 $end
$var reg 1 3 b4 $end
$var reg 1 4 b5 $end
$var reg 1 5 b6 $end
$var reg 1 6 b7 $end
$var reg 1 7 b8 $end
$var reg 1 8 b9 $end
$scope module m21 $end
$var wire 1 - A $end
$var wire 1 . B $end
$var wire 1 / C $end
$var wire 1 $ y $end
$scope module c1 $end
$var wire 1 9 d0 $end
$var wire 1 : d1 $end
$var wire 1 - s $end
$var wire 1 $ y $end
$upscope $end
$upscope $end
$scope module m41 $end
$var wire 1 * A $end
$var wire 1 + B $end
$var wire 1 , C $end
$var wire 1 % y $end
$scope module f1 $end
$var wire 1 , d0 $end
$var wire 1 ; d1 $end
$var wire 1 < d2 $end
$var wire 1 , d3 $end
$var wire 1 + s0 $end
$var wire 1 * s1 $end
$var wire 1 % y $end
$var wire 1 = l1 $end
$var wire 1 > h1 $end
$scope module highmux $end
$var wire 1 < d0 $end
$var wire 1 , d1 $end
$var wire 1 + s $end
$var wire 1 > y $end
$upscope $end
$scope module lowmux $end
$var wire 1 , d0 $end
$var wire 1 ; d1 $end
$var wire 1 + s $end
$var wire 1 = y $end
$upscope $end
$scope module outmux $end
$var wire 1 = d0 $end
$var wire 1 > d1 $end
$var wire 1 * s $end
$var wire 1 % y $end
$upscope $end
$upscope $end
$upscope $end
$scope module m81 $end
$var wire 1 ' A $end
$var wire 1 ( B $end
$var wire 1 ) C $end
$var wire 1 ? h $end
$var wire 1 @ l $end
$var wire 1 & Y $end
$scope module fun1 $end
$var wire 1 @ d0 $end
$var wire 1 ? d1 $end
$var wire 1 ? d2 $end
$var wire 1 @ d3 $end
$var wire 1 ? d4 $end
$var wire 1 @ d5 $end
$var wire 1 @ d6 $end
$var wire 1 ? d7 $end
$var wire 1 ) s $end
$var wire 1 ( s1 $end
$var wire 1 ' s2 $end
$var wire 1 & y $end
$var wire 1 A sal2 $end
$var wire 1 B sal1 $end
$scope module fun1 $end
$var wire 1 @ d0 $end
$var wire 1 ? d1 $end
$var wire 1 ? d2 $end
$var wire 1 @ d3 $end
$var wire 1 ) s0 $end
$var wire 1 ( s1 $end
$var wire 1 B y $end
$var wire 1 C l1 $end
$var wire 1 D h1 $end
$scope module highmux $end
$var wire 1 ? d0 $end
$var wire 1 @ d1 $end
$var wire 1 ) s $end
$var wire 1 D y $end
$upscope $end
$scope module lowmux $end
$var wire 1 @ d0 $end
$var wire 1 ? d1 $end
$var wire 1 ) s $end
$var wire 1 C y $end
$upscope $end
$scope module outmux $end
$var wire 1 C d0 $end
$var wire 1 D d1 $end
$var wire 1 ( s $end
$var wire 1 B y $end
$upscope $end
$upscope $end
$scope module fun2 $end
$var wire 1 ? d0 $end
$var wire 1 @ d1 $end
$var wire 1 @ d2 $end
$var wire 1 ? d3 $end
$var wire 1 ) s0 $end
$var wire 1 ( s1 $end
$var wire 1 A y $end
$var wire 1 E l1 $end
$var wire 1 F h1 $end
$scope module highmux $end
$var wire 1 @ d0 $end
$var wire 1 ? d1 $end
$var wire 1 ) s $end
$var wire 1 F y $end
$upscope $end
$scope module lowmux $end
$var wire 1 ? d0 $end
$var wire 1 @ d1 $end
$var wire 1 ) s $end
$var wire 1 E y $end
$upscope $end
$scope module outmux $end
$var wire 1 E d0 $end
$var wire 1 F d1 $end
$var wire 1 ( s $end
$var wire 1 A y $end
$upscope $end
$upscope $end
$scope module fun3 $end
$var wire 1 B d0 $end
$var wire 1 A d1 $end
$var wire 1 ' s $end
$var wire 1 & y $end
$upscope $end
$upscope $end
$upscope $end
$scope module x21 $end
$var wire 1 6 A $end
$var wire 1 7 B $end
$var wire 1 8 C $end
$var wire 1 ! y $end
$scope module b2 $end
$var wire 1 G d0 $end
$var wire 1 H d1 $end
$var wire 1 6 s $end
$var wire 1 ! y $end
$upscope $end
$upscope $end
$scope module x41 $end
$var wire 1 3 A $end
$var wire 1 4 B $end
$var wire 1 5 C $end
$var wire 1 I l $end
$var wire 1 " y $end
$scope module f2 $end
$var wire 1 J d0 $end
$var wire 1 I d1 $end
$var wire 1 5 d2 $end
$var wire 1 K d3 $end
$var wire 1 4 s0 $end
$var wire 1 3 s1 $end
$var wire 1 " y $end
$var wire 1 L l1 $end
$var wire 1 M h1 $end
$scope module highmux $end
$var wire 1 5 d0 $end
$var wire 1 K d1 $end
$var wire 1 4 s $end
$var wire 1 M y $end
$upscope $end
$scope module lowmux $end
$var wire 1 J d0 $end
$var wire 1 I d1 $end
$var wire 1 4 s $end
$var wire 1 L y $end
$upscope $end
$scope module outmux $end
$var wire 1 L d0 $end
$var wire 1 M d1 $end
$var wire 1 3 s $end
$var wire 1 " y $end
$upscope $end
$upscope $end
$upscope $end
$scope module x81 $end
$var wire 1 0 A $end
$var wire 1 1 B $end
$var wire 1 2 C $end
$var wire 1 N h $end
$var wire 1 O l $end
$var wire 1 # y $end
$scope module fun2 $end
$var wire 1 N d0 $end
$var wire 1 N d1 $end
$var wire 1 O d2 $end
$var wire 1 O d3 $end
$var wire 1 N d4 $end
$var wire 1 N d5 $end
$var wire 1 N d6 $end
$var wire 1 O d7 $end
$var wire 1 2 s $end
$var wire 1 1 s1 $end
$var wire 1 0 s2 $end
$var wire 1 # y $end
$var wire 1 P sal2 $end
$var wire 1 Q sal1 $end
$scope module fun1 $end
$var wire 1 N d0 $end
$var wire 1 N d1 $end
$var wire 1 O d2 $end
$var wire 1 O d3 $end
$var wire 1 2 s0 $end
$var wire 1 1 s1 $end
$var wire 1 Q y $end
$var wire 1 R l1 $end
$var wire 1 S h1 $end
$scope module highmux $end
$var wire 1 O d0 $end
$var wire 1 O d1 $end
$var wire 1 2 s $end
$var wire 1 S y $end
$upscope $end
$scope module lowmux $end
$var wire 1 N d0 $end
$var wire 1 N d1 $end
$var wire 1 2 s $end
$var wire 1 R y $end
$upscope $end
$scope module outmux $end
$var wire 1 R d0 $end
$var wire 1 S d1 $end
$var wire 1 1 s $end
$var wire 1 Q y $end
$upscope $end
$upscope $end
$scope module fun2 $end
$var wire 1 N d0 $end
$var wire 1 N d1 $end
$var wire 1 N d2 $end
$var wire 1 O d3 $end
$var wire 1 2 s0 $end
$var wire 1 1 s1 $end
$var wire 1 P y $end
$var wire 1 T l1 $end
$var wire 1 U h1 $end
$scope module highmux $end
$var wire 1 N d0 $end
$var wire 1 O d1 $end
$var wire 1 2 s $end
$var wire 1 U y $end
$upscope $end
$scope module lowmux $end
$var wire 1 N d0 $end
$var wire 1 N d1 $end
$var wire 1 2 s $end
$var wire 1 T y $end
$upscope $end
$scope module outmux $end
$var wire 1 T d0 $end
$var wire 1 U d1 $end
$var wire 1 1 s $end
$var wire 1 P y $end
$upscope $end
$upscope $end
$scope module fun3 $end
$var wire 1 Q d0 $end
$var wire 1 P d1 $end
$var wire 1 0 s $end
$var wire 1 # y $end
$upscope $end
$upscope $end
$upscope $end
$upscope $end
$enddefinitions $end
#0
$dumpvars
xU
1T
0S
1R
xQ
xP
0O
1N
xM
xL
xK
xJ
0I
xH
xG
0F
1E
1D
0C
0B
1A
0@
1?
x>
x=
x<
x;
x:
x9
x8
x7
x6
x5
x4
x3
x2
x1
x0
x/
x.
x-
x,
x+
x*
0)
0(
0'
0&
x%
x$
x#
x"
x!
$end
#1
1&
1B
0A
0D
1C
1F
0E
1)
#2
1&
1D
0C
0F
1E
1B
0A
0)
1(
#3
0&
0B
1A
0D
1C
1F
0E
1)
#4
1D
0C
0F
1E
0B
1A
1&
0)
0(
1'
#5
0&
1B
0A
0D
1C
1F
0E
1)
#6
0&
1D
0C
0F
1E
1B
0A
0)
1(
#7
1&
0B
1A
0D
1C
1F
0E
1)
#9
1>
0%
1;
1<
0=
0,
0+
0*
#10
0>
1%
0;
0<
1=
1,
#11
1%
1;
1<
1=
0,
1+
#12
0%
0=
0;
0<
1>
1,
#13
1;
1<
1>
1%
0,
0+
1*
#14
0%
0>
0;
0<
1=
1,
#15
1;
1<
1=
0,
1+
#16
0=
1%
0;
0<
1>
1,
#17
0$
09
1:
0/
0.
0-
#18
1$
19
0:
1/
#19
0/
1.
#20
0$
09
1:
1/
#21
1$
0/
0.
1-
#22
0$
19
0:
1/
#23
0/
1.
#24
1$
09
1:
1/
#25
1#
1U
1Q
1P
02
01
00
#26
0U
12
#27
0#
1U
0Q
1P
02
11
#28
0P
0U
12
#29
1#
1U
1Q
1P
02
01
10
#30
0U
12
#31
1#
1U
0Q
1P
02
11
#32
0#
0P
0U
12
#33
1"
1L
1J
1K
0M
05
04
03
#34
0"
0L
0J
0K
1M
15
#35
1J
1K
1M
05
14
#36
0M
0J
0K
15
#37
1L
1J
1K
05
04
13
#38
0L
1"
0J
0K
1M
15
#39
1"
1J
1K
1M
05
14
#40
0"
0M
0J
0K
15
#41
1!
1G
1H
08
07
06
#42
0!
0G
18
#43
08
17
#44
0H
18
#45
1!
1G
1H
08
07
16
#46
0G
18
#47
08
17
#48
0!
0H
18
