LAB3/EC1/Ecuacion1.v
//Francisco Montúfar #19379
//Archivo de la POS de la tabla 1

module Ecuacion1(); //se crea el módulo

reg A;    //Se crean las variables de entrada, en este caso A, B y C
reg B;
reg C;

wire sal1;
wire sal2;
wire sal3; // variables de las salidas, en este caso son las salidas de los NOT
wire sal4;
wire sal5;
wire sal6; //variables de salida de los OR
wire Y; // variable de salida del AND

not s0(sal1, A);
not s1(sal2, B); //comandos para realizar la operacion de la compuerta
not s2(sal3, C); //en este caso son NOT, la estructura es [Compuerta nombre(salida,entrada(s))]

or s3(sal4, A, B, sal3);
or s4(sal5, A, sal2, sal3); //comandos para realizar la operacion de la compuerta
or s5(sal6, sal1, sal2, C); //en este caso son OR

and s6(Y, sal4, sal5, sal6); //comando para el AND, ojo: se usan de entradas las salidas de los anteriores.

// Iniciar operaciones

initial begin

  $display("A B C | Y"); // se agrega un formato para facilitar comprension
  $display("------------");

  $monitor("%b %b %b | %b", A, B, C, Y); //monitorea las variables con el formato dado
  A = 0; B = 0; C = 0;  //condiciones iniciales de las entradas
  #1 C = 1;
  #1 B = 1; C = 0;
  #1 C = 1;
  #1 A = 1; B = 0; C = 0;  // se van cambiando los valores depende a la tabla
  #1 C = 1;
  #1 B = 1; C = 0;
  #1 C = 1;
  #1 $finish;
end

//habilitar GTKWave
  initial
      begin
          $dumpfile("Ecuacion1_tb.vcd");
          $dumpvars (0, Ecuacion1);
      end
endmodule

LAB3/EC1/Ecuacion1_tb.vcd
$date
	Sun Aug 02 12:51:06 2020
$end
$version
	Icarus Verilog
$end
$timescale
	1ps
$end
$scope module Ecuacion1 $end
$var wire 1 ! Y $end
$var wire 1 " sal1 $end
$var wire 1 # sal2 $end
$var wire 1 $ sal3 $end
$var wire 1 % sal4 $end
$var wire 1 & sal5 $end
$var wire 1 ' sal6 $end
$var reg 1 ( A $end
$var reg 1 ) B $end
$var reg 1 * C $end
$upscope $end
$enddefinitions $end
#0
$dumpvars
0*
0)
0(
1'
1&
1%
1$
1#
1"
1!
$end
#1
0!
0%
0$
1*
#2
1!
1$
1%
0#
0*
1)
#3
0!
0&
0$
1*
#4
1!
1$
1#
1&
0"
0*
0)
1(
#5
0$
1*
#6
0!
0'
1$
0#
0*
1)
#7
1!
1'
0$
1*
