LAB9/Ej2/Ejercicio_2.v
module FlipF(input wire clk, reset, EN,
            input wire D,
            output reg Q);

always @ (posedge clk or posedge reset)begin
  if (reset) begin
      Q <= 1'b0;
      end
  else if (EN) begin
      Q <= D;
      end
  end

endmodule


module FlipFT(input wire clk, reset, EN,
              output wire Q1);

    wire D;
    not (D, Q1);
    FlipF  a1(clk, reset, EN, D, Q1);

endmodule

LAB9/Ej2/Ejercicio2_tb.v
module testbench();
  reg clk, reset, EN;
  reg T;
  wire Q1;
FlipFT  a1(clk, reset, EN, Q1);



  always
  #1 clk  = ~clk;


initial begin

$display(" ejercicio 2");
$display ("clk RST EN | T | Q1");
$display("----------------------------|------------");
$monitor("%b %b %b %b   | %b", clk, reset, EN, T, Q1);
      clk = 0; reset = 0; EN = 0; T = 0;
   #2 reset = 1;
   #2 reset = 0;
   #2 EN = 1;
   #2 T = 1;


end

initial
  #25 $finish;

  initial begin
  $dumpfile("Ejercicio2_tb.vcd");
  $dumpvars(0, testbench);
end
endmodule

LAB9/Ej2/Ejercicio2_tb.vcd
$date
	Fri Oct 30 19:22:02 2020
$end
$version
	Icarus Verilog
$end
$timescale
	1ps
$end
$scope module testbench $end
$var wire 1 ! Q1 $end
$var reg 1 " EN $end
$var reg 1 # T $end
$var reg 1 $ clk $end
$var reg 1 % reset $end
$scope module a1 $end
$var wire 1 & D $end
$var wire 1 " EN $end
$var wire 1 $ clk $end
$var wire 1 % reset $end
$var wire 1 ! Q1 $end
$scope module a1 $end
$var wire 1 & D $end
$var wire 1 " EN $end
$var wire 1 $ clk $end
$var wire 1 % reset $end
$var reg 1 ! Q $end
$upscope $end
$upscope $end
$upscope $end
$enddefinitions $end
#0
$dumpvars
x&
0%
0$
0#
0"
x!
$end
#1
1$
#2
1&
0!
0$
1%
#3
1$
#4
0$
0%
#5
1$
#6
0$
1"
#7
0&
1!
1$
#8
0$
1#
#9
1&
0!
1$
#10
0$
#11
0&
1!
1$
#12
0$
#13
1&
0!
1$
#14
0$
#15
0&
1!
1$
#16
0$
#17
1&
0!
1$
#18
0$
#19
0&
1!
1$
#20
0$
#21
1&
0!
1$
#22
0$
#23
0&
1!
1$
#24
0$
#25
1&
0!
1$
