LAB3/EC5/Ecuacion5.v
//Francisco Montúfar #19379
//Archivo de la SOP de la tabla 3

module Ecuacion5(); //se crea el módulo

reg A;
reg B;
reg C;
reg D;  //Se crean las variables de entrada, en este caso A, B, C y D

wire sal1;
wire sal2;
wire sal3;
wire sal4; // variables de las salidas, en este caso son las salidas de los NOT
wire sal5;
wire sal6;
wire sal7;
wire sal8;
wire sal9;
wire sal10;
wire sal11; //variables de salida de los AND
wire Y;     //variable de salida del OR

not s0(sal1, A);
not s1(sal2, B);
not s2(sal3, C); //comandos para realizar la operacion de la compuerta
not s3(sal4, D); //en este caso son NOT, la estructura es [Compuerta nombre(salida,entrada(s))]

and s4(sal5, sal1, sal2, sal3, sal4);
and s5(sal6, sal1, sal2, sal3, D);
and s6(sal7, sal1, sal2, C, sal4);
and s7(sal8, sal1, sal2, C, D);
and s8(sal9, A, sal2, sal3, sal4);
and s9(sal10, A, sal2, C, sal4); //comandos para realizar operacion de compuerta
and s10(sal11, A, B, C, sal4);   //en este caso son AND

or s11(Y, sal5, sal6, sal7, sal8, sal9, sal10, sal11); //comando para el OR, ojo: se usan de entradas las salidas de los anteriores

// iniciar operaciones
initial begin

  $display("A B C D | Y"); // se agrega un formato para facilitar comprension
  $display("------------");

  $monitor("%b %b %b %b | %b", A, B, C, D, Y); //monitorea las variables con el formato dado
  A = 0; B = 0; C = 0; D = 0;  //condiciones iniciales de las entradas
  #1 D = 1;
  #1 C = 1; D = 0;
  #1 D = 1;
  #1 B = 1; C = 0; D = 0;
  #1 D = 1;
  #1 C = 1; D = 0;
  #1 D = 1;
  #1 A = 1; B = 0; C = 0; D = 0;
  #1 D = 1;
  #1 C = 1; D = 0;
  #1 D = 1;
  #1 B = 1; C = 0; D = 0;
  #1 D = 1;
  #1 C = 1;  D = 0;
  #1 D = 1;
  #1 $finish;
end

//habilitar GTKWave
  initial
      begin
          $dumpfile("Ecuacion5_tb.vcd");
          $dumpvars (0, Ecuacion5);
      end
endmodule

LAB3/EC5/Ecuacion5_tb.vcd
$date
	Sun Aug 02 12:48:23 2020
$end
$version
	Icarus Verilog
$end
$timescale
	1ps
$end
$scope module Ecuacion5 $end
$var wire 1 ! Y $end
$var wire 1 " sal1 $end
$var wire 1 # sal10 $end
$var wire 1 $ sal11 $end
$var wire 1 % sal2 $end
$var wire 1 & sal3 $end
$var wire 1 ' sal4 $end
$var wire 1 ( sal5 $end
$var wire 1 ) sal6 $end
$var wire 1 * sal7 $end
$var wire 1 + sal8 $end
$var wire 1 , sal9 $end
$var reg 1 - A $end
$var reg 1 . B $end
$var reg 1 / C $end
$var reg 1 0 D $end
$upscope $end
$enddefinitions $end
#0
$dumpvars
00
0/
0.
0-
0,
0+
0*
0)
1(
1'
1&
1%
0$
0#
1"
1!
$end
#1
0(
1)
0'
10
#2
1*
0)
1'
0&
00
1/
#3
0*
1+
0'
10
#4
0!
1'
0+
1&
0%
00
0/
1.
#5
0'
10
#6
1'
0&
00
1/
#7
0'
10
#8
1!
1,
1'
1&
1%
0"
00
0/
0.
1-
#9
0!
0,
0'
10
#10
1!
1#
1'
0&
00
1/
#11
0!
0#
0'
10
#12
1'
1&
0%
00
0/
1.
#13
0'
10
#14
1!
1$
1'
0&
00
1/
#15
0!
0$
0'
10
