LAB8/Ej2/Ejercicio_2.v
//ROM

module  memrom(input wire [11:0]D, output wire [7:0]Dout); //se indican las entradas y salidas

assign Dout = larom[D]; // se establece que lo que saca la memoria es lo mismo que le entra
reg [7:0]   larom[0:4095]; //se declara el width y el depth de la memoria

initial begin
  $readmemh("lista.memoria", larom); // se establece que se lea en hexadecimal lo del archivo (lo que entra) y salida
  end

endmodule

LAB8/Ej2/Ejercicio2_tb.v
module testbench();
reg [11:0]D; //input
wire [0:7]Dout; //salidas

memrom  u1 (D, Dout);



initial begin
$display ("\n");
$display(" ROM ");
$display ("D | D| Dout | Dout");
$display("---------|------------");
$monitor(" %h | %b  | %h | %b ", D, D, Dout, Dout);
#1 D = 0;
#1 D = 1;
#1 D = 2;
#1 D = 3;
#1 D = 4;
#1 D = 5;
#1 D = 6;
#1 D = 7;
#1 D = 8;
#1 D = 9;
#1 D = 10;
#1 D = 4094;


  end

  initial
    #145 $finish;

  initial begin
    $dumpfile("Ejercicio2_tb.vcd");
    $dumpvars(0, testbench);

  end
  endmodule

LAB8/Ej2/Ejercicio2_tb.vcd
$date
	Sat Oct 24 19:48:01 2020
$end
$version
	Icarus Verilog
$end
$timescale
	1ps
$end
$scope module testbench $end
$var wire 8 ! Dout [0:7] $end
$var reg 12 " D [11:0] $end
$scope module u1 $end
$var wire 12 # D [11:0] $end
$var wire 8 $ Dout [7:0] $end
$upscope $end
$upscope $end
$enddefinitions $end
#0
$dumpvars
bx $
bx #
bx "
bx !
$end
#1
b11011101 !
b11011101 $
b0 "
b0 #
#2
b1000101 !
b1000101 $
b1 "
b1 #
#3
b1101 !
b1101 $
b10 "
b10 #
#4
b1010101 !
b1010101 $
b11 "
b11 #
#5
b1000100 !
b1000100 $
b100 "
b100 #
#6
b11111111 !
b11111111 $
b101 "
b101 #
#7
b1100110 !
b1100110 $
b110 "
b110 #
#8
b10101010 !
b10101010 $
b111 "
b111 #
#9
b10001000 !
b10001000 $
b1000 "
b1000 #
#10
b11011101 !
b11011101 $
b1001 "
b1001 #
#11
b10001 !
b10001 $
b1010 "
b1010 #
#12
bx !
bx $
b111111111110 "
b111111111110 #
