LAB6/lab_6.v
//FRANCISCO MONTÚFAR
//CARNET 19379







//Ejercicio 6 con rst asincrono

module FLIPflop (input clk, reset, D,
            output reg Q);
        always @ (posedge clk or posedge reset)begin
            if (reset) begin
                Q <= 1'b0;
            end
            else begin
                Q <= D;
            end
        end
endmodule

//ejercicio 1

module  ejer1(input A, B, clk, reset, output wire Q, output wire [1:0] S2, F2);
wire S0, S1, F0, F1;

        assign  F0 = (~S1 & ~S0 & A);
        assign F1 = (S0 & B) | (S1 & A & B);

        FLIPflop U1(clk, reset, F0, S0);
        FLIPflop U2(clk, reset, F1, S1);
        assign Q = (S1 & ~S0 & A & B);
        assign S2 = {S1, S0};
        assign F2 = {F1, F0};

endmodule

module ejer3 (input A, clk, reset,
output Y3, Y2, Y1,
output wire [2:0]F3, S3);
wire S0, S1, S2, F0, F1, F2;

assign F0 = ~S0;
assign F1 = (~S1 & ~S0 & ~A) | (S1 & S0 & ~A) | (S1 & ~S0 & A) | (~S1 & S0 & A);
assign F2 = (S2 & S1 & ~A) | (S2 & ~S0 & A) | (S2 & ~S1 & S0) | (~S2 & ~S1 & ~S0 & ~A) | (~S2 & S1 & S0 & A);

FLIPflop  C0(clk, reset, F0, S0);
FLIPflop  C1(clk, reset, F1, S1);
FLIPflop  C3(clk, reset, F2, S2);


assign S3 = {S2, S1, S0};
assign F3 = {F2, F1, F0};
assign Y3 = S2;
assign Y2 = (S2 & ~S1) | (~S2 & S1);
assign Y1 = (S1 & ~S0) | (~S1 & S0);

endmodule

LAB6/lab6_tb.v
//testbench
// ejercicio 6
module testbench();


reg clk, reset;
reg A, B, A1;
wire [1:0] F, P;
wire Q;
wire [2:0] F2, P2;




  ejer1  a1(A, B, clk, reset, Q, P, F);
  ejer3  a2(A1, clk, reset,Q1, Q2, Q3, F2, P2);

initial begin
        $display("\n");
        $display("Ejercicio 1");
        $display("reset A B F P Q");
        $monitor("%b %b %b %b %b %b", reset, A, B, F, P, Q);
           A = 0; B = 0; clk = 0; reset = 0;
        #1   reset = 1;
        #1   A = 1; B = 1; reset = 0;


    end



 initial begin
        #7
        $display("\n");
        $display("Ejercicio 3");
        $display("reset A1  F2 P2 Q1 Q2 Q3");
        $monitor("%b      %b   %b  %b   %b  %b  %b", reset, A1, F2, P2, Q1, Q2, Q3);
            reset = 1; A1 = 1;
        #8 A1 = 1; reset = 0;
        #2 A1 = 0;

    end


    always
        #5 clk = ~clk;


  initial
      #40 $finish;

      initial begin
        $dumpfile("lab6_tb.vcd");
        $dumpvars(0, testbench);
      end

endmodule

LAB6/lab6_tb.vcd
$date
	Sat Sep 05 22:15:00 2020
$end
$version
	Icarus Verilog
$end
$timescale
	1ps
$end
$scope module testbench $end
$var wire 1 ! Q3 $end
$var wire 1 " Q2 $end
$var wire 1 # Q1 $end
$var wire 1 $ Q $end
$var wire 3 % P2 [2:0] $end
$var wire 2 & P [1:0] $end
$var wire 3 ' F2 [2:0] $end
$var wire 2 ( F [1:0] $end
$var reg 1 ) A $end
$var reg 1 * A1 $end
$var reg 1 + B $end
$var reg 1 , clk $end
$var reg 1 - reset $end
$scope module a1 $end
$var wire 1 ) A $end
$var wire 1 + B $end
$var wire 1 . F0 $end
$var wire 1 / F1 $end
$var wire 1 $ Q $end
$var wire 1 , clk $end
$var wire 1 - reset $end
$var wire 2 0 S2 [1:0] $end
$var wire 1 1 S1 $end
$var wire 1 2 S0 $end
$var wire 2 3 F2 [1:0] $end
$scope module U1 $end
$var wire 1 . D $end
$var wire 1 , clk $end
$var wire 1 - reset $end
$var reg 1 2 Q $end
$upscope $end
$scope module U2 $end
$var wire 1 / D $end
$var wire 1 , clk $end
$var wire 1 - reset $end
$var reg 1 1 Q $end
$upscope $end
$upscope $end
$scope module a2 $end
$var wire 1 * A $end
$var wire 1 4 F0 $end
$var wire 1 5 F1 $end
$var wire 1 6 F2 $end
$var wire 1 ! Y1 $end
$var wire 1 " Y2 $end
$var wire 1 # Y3 $end
$var wire 1 , clk $end
$var wire 1 - reset $end
$var wire 3 7 S3 [2:0] $end
$var wire 1 8 S2 $end
$var wire 1 9 S1 $end
$var wire 1 : S0 $end
$var wire 3 ; F3 [2:0] $end
$scope module C0 $end
$var wire 1 4 D $end
$var wire 1 , clk $end
$var wire 1 - reset $end
$var reg 1 : Q $end
$upscope $end
$scope module C1 $end
$var wire 1 5 D $end
$var wire 1 , clk $end
$var wire 1 - reset $end
$var reg 1 9 Q $end
$upscope $end
$scope module C3 $end
$var wire 1 6 D $end
$var wire 1 , clk $end
$var wire 1 - reset $end
$var reg 1 8 Q $end
$upscope $end
$upscope $end
$upscope $end
$enddefinitions $end
#0
$dumpvars
bx ;
x:
x9
x8
bx 7
x6
x5
x4
b0 3
x2
x1
bx 0
0/
0.
0-
0,
0+
x*
0)
b0 (
bx '
bx &
bx %
0$
x#
x"
x!
$end
#1
0!
0"
bx1 '
bx1 ;
14
02
b0 &
b0 0
01
0:
09
b0 %
b0 7
0#
08
1-
#2
b1 (
b1 3
1.
0-
1+
1)
#5
0.
x"
x!
b10 (
b10 3
1/
bx0 '
bx0 ;
04
x#
x8
x9
bx1 %
bx1 7
1:
b1 &
b1 0
12
1,
#7
1.
06
05
b1 (
b1 3
0/
0!
0"
b1 '
b1 ;
14
b0 &
b0 0
02
0:
09
b0 %
b0 7
0#
08
1*
1-
#10
0,
#15
15
0.
1!
b10 (
b10 3
1/
b10 '
b10 ;
04
b1 %
b1 7
1:
b1 &
b1 0
12
1,
0-
#17
b0 '
b0 ;
05
0*
#20
0,
#25
15
16
1$
0!
b111 '
b111 ;
14
02
b10 &
b10 0
11
b0 %
b0 7
0:
1,
#30
0,
#35
16
0"
0!
b110 '
b110 ;
04
1#
18
19
b111 %
b111 7
1:
1,
