LAB3/EC8/Ecuacion8.v
//Francisco Montúfar #19379
//Archivo de la POS de la tabla 4

module Ecuacion8();

reg A;
reg B;
reg C;
reg D;  //Se crean las variables de entrada, en este caso A, B, C y D

wire sal1;
wire sal2;
wire sal3;
wire sal4; // variables de las salidas, en este caso son las salidas de los NOT
wire sal5;
wire sal6;
wire sal7;
wire sal8;
wire sal9;
wire sal10;
wire sal11;
wire sal12;
wire sal13; //variables de salida del OR
wire Y;     //variable de salida del AND

not s0(sal1, A);
not s1(sal2, B);
not s2(sal3, C); //comandos para realizar la operacion de la compuerta
not s3(sal4, D); //en este caso son NOT, la estructura es [Compuerta nombre(salida,entrada(s))]

or s4(sal5, A, B, C, sal4);
or s5(sal6, A, sal2, C, D);
or s6(sal7, A, sal2, C, sal4);
or s7(sal8, sal1, B, C, sal4);
or s8 (sal9, sal1, B, sal3, sal4);
or s9(sal10, sal1, sal2, C, D);
or s10 (sal11, sal1, sal2, C, sal4);
or s11 (sal12, sal1, sal2, sal3, D); //comandos para realizar operacion
or s12 (sal13, sal1, sal2, sal3, sal4); //en este caso es OR

and s13(Y, sal5, sal6, sal7, sal8, sal9, sal10, sal11, sal12, sal13);  //comando para el AND, ojo: se usan de entradas las salidas de los anteriores

// iniciar operaciones
initial begin

  $display("A B C D | Y"); // se agrega un formato para facilitar comprension
  $display("------------");

  $monitor("%b %b %b %b | %b", A, B, C, D, Y); //monitorea las variables con el formato dado
  A = 0; B = 0; C = 0; D = 0;  //condiciones iniciales de las entradas
  #1 D = 1;
  #1 C = 1; D = 0;
  #1 D = 1;
  #1 B = 1; C = 0; D = 0;
  #1 D = 1;
  #1 C = 1; D = 0;
  #1 D = 1;
  #1 A = 1; B = 0; C = 0; D = 0;
  #1 D = 1;
  #1 C = 1; D = 0;
  #1 D = 1;
  #1 B = 1; C = 0; D = 0;
  #1 D = 1;
  #1 C = 1;  D = 0;
  #1 D = 1;
  #1 $finish;
end

//habilitar GTKWave
  initial
      begin
          $dumpfile("Ecuacion8_tb.vcd");
          $dumpvars (0, Ecuacion8);
      end
endmodule

LAB3/EC8/Ecuacion8_tb.vcd
$date
	Sun Aug 02 12:46:11 2020
$end
$version
	Icarus Verilog
$end
$timescale
	1ps
$end
$scope module Ecuacion8 $end
$var wire 1 ! Y $end
$var wire 1 " sal1 $end
$var wire 1 # sal10 $end
$var wire 1 $ sal11 $end
$var wire 1 % sal12 $end
$var wire 1 & sal13 $end
$var wire 1 ' sal2 $end
$var wire 1 ( sal3 $end
$var wire 1 ) sal4 $end
$var wire 1 * sal5 $end
$var wire 1 + sal6 $end
$var wire 1 , sal7 $end
$var wire 1 - sal8 $end
$var wire 1 . sal9 $end
$var reg 1 / A $end
$var reg 1 0 B $end
$var reg 1 1 C $end
$var reg 1 2 D $end
$upscope $end
$enddefinitions $end
#0
$dumpvars
02
01
00
0/
1.
1-
1,
1+
1*
1)
1(
1'
1&
1%
1$
1#
1"
1!
$end
#1
0!
0*
0)
12
#2
1!
1)
1*
0(
02
11
#3
0)
12
#4
0!
1)
1,
0+
1(
0'
02
01
10
#5
0,
1+
0)
12
#6
1!
1)
1,
0(
02
11
#7
0)
12
#8
1!
1)
1(
1.
1-
1'
0"
02
01
00
1/
#9
0!
0-
0)
12
#10
1!
1)
1-
0(
02
11
#11
0!
0.
0)
12
#12
1)
1$
0#
1(
1.
0'
02
01
10
#13
0$
1#
0)
12
#14
0%
1)
1$
0(
02
11
#15
0&
1%
0)
12
