PROYECTO/PROYECTO.v
//Proyecto
//Flip flop tipo D de 3 bits, reset asíncrono
module FlipF3(input wire clk, reset, E,
              input wire [2:0]D,
              output reg [2:0]Q);
always @ (posedge clk or posedge reset)begin
  if (reset) begin
      Q <= 3'b0;
end
else if (E) begin
Q <= D;
end
end
endmodule

//Flip flop tipo D de 2 bits, reset asíncrono
module FlipF2(input wire clk, reset, E,
            input wire [1:0]D,
            output reg [1:0]Q);
always @ (posedge clk or posedge reset)begin
  if (reset) begin
      Q <= 2'b0;
  end
  else if (E) begin
  Q <= D;
  end
end
endmodule

//Flip flop tipo de de 1 bit, reset asíncrono
module FlipF1(input wire clk, reset,E,
            input wire D,
            output reg Q);
always @ (posedge clk or posedge reset)begin
  if (reset) begin
      Q <= 1'b0;
  end
  else if (E) begin
  Q <= D;
  end
end

endmodule

//Antirebote
module antireb (input wire clk, reset, PB, output wire Q);
wire Y1, Y2;
assign Y2 = (PB);
FlipF1  F1(clk, reset, 1'b1 , Y2, Y1);
assign Q = (~Y1 & PB);
endmodule

//selector de local
module selector(input wire reset, clk, PB1, PB2, output wire E, E1);
wire s0, s1;
wire [1:0]s;
wire [1:0]sf;
assign s1 = s[1];
assign s0 = s[0];
assign sf[1] = (~s1 & ~s0 & PB2 & ~PB1) | (s1 & ~s0 & ~PB2 & ~ PB1) | (s1 & ~s0 & ~PB2 & PB1) | (s1 & ~s0 & PB2 & PB1);
assign sf[0] = (~s1 & ~s0 & ~PB2 & PB1) | (~s1 & s0 & ~PB2 & ~PB1) | (~s1 & s0 & PB2 & PB1) | (~s1 & s0 & PB2 & PB1);
FlipF2  t1(clk, reset, 1'b1, sf, s);
assign E = (~s1 & s0);
assign E1 = (s1 & ~s0);
endmodule

//modulo del car carwash
module carwash(input wire reset, clk, EN, input wire[3:0]L, input wire BF, output wire CT0, output wire [2:0]SA);
wire sc0, sc1, sc2;
wire [2:0]s_c;
wire [2:0]sf_c;
assign sc2 = s_c[2];
assign sc1 = s_c[1];
assign sc0 = s_c[0];

assign sf_c[2] = (~sc2 & sc1 & ~sc0 & ~L[3] & ~L[2] & ~L[1] & L[0] & BF) | (~sc2 & sc1 & sc0 & L[3] & ~L[2] & ~L[1] & ~L[0] & BF) | (~sc2 & sc1 & sc0 & ~L[3] & L[2] & ~L[1] & ~L[0] & BF) |
                 (~sc2 & ~sc1 & sc0 & ~L[3] & ~L[2] & L[1] & ~L[0] & BF) | (sc2 & ~sc1 & sc0 & ~L[3] & ~L[2] & L[1] & ~L[0] & ~BF) | (sc2 & ~sc1 & sc0 & ~L[3] & ~L[2] & ~L[1] & L[0] & ~BF) |
                 (sc2 & ~sc1 & ~sc0 & L[3] & ~L[2] & ~L[1] & ~L[0]) | (sc2 & ~sc1 & ~sc0 & ~L[3] & L[2] & ~L[1] & ~L[0]) | (sc2 & ~sc1 & L[3] & ~L[2] & ~L[1] & ~L[0] & ~BF) |
                 (sc2 & ~sc1 & ~L[3] & L[2] & ~L[1] & ~L[0] & ~BF);

assign sf_c[1] = (~sc2 & ~sc1 & ~sc0 & ~L[3] & L[2] & ~L[1] & ~L[0] & BF) | (~sc2 & ~sc1 & sc0 & ~L[3] & ~L[2] & ~L[1] & L[0] & BF) | (~sc2 & sc1 & sc0 & ~L[3] & L[2] & ~L[1] & ~L[0] & ~BF) |
                 (~sc2 & sc1 & ~sc0 & ~L[3] & ~L[2] & ~L[1] & L[0] & ~BF) | (~sc2 & ~sc1 & sc0 & L[3] & ~L[2] & ~L[1] & ~L[0] & BF) | (~sc2 & sc1 & L[3] & ~L[2] & ~L[1] & ~L[0] & ~BF) |
                 (~sc2 & sc1 & ~sc0 & L[3] & ~L[2] & ~L[1] & ~L[0]);

assign sf_c[0] = (~sc2 & ~sc0 & ~L[3] & ~L[2] & ~L[1] & L[0] & BF) | (~sc2 & sc1 & sc0 & ~L[3] & L[2] & ~L[1] & ~L[0] & ~BF) | (~sc2 & ~sc0 & L[3] & ~L[2] & ~L[1] & ~L[0] & BF) |
                 (~sc1 & ~sc0 & ~L[3] & L[2] & ~L[1] & ~L[0] & BF) | (~sc2 & sc0 & L[3] & ~L[2] & ~L[1] & ~L[0] & ~BF) | (sc2 & ~sc1 & sc0 & ~L[3] & L[2] & ~L[1] & ~L[0] & ~BF) |
                 (~sc1 & sc0 & ~L[3] & ~L[2] & L[1] & ~L[0] & ~BF) | (~sc1 & sc0 & ~L[3] & ~L[2] & ~L[1] & L[0] & ~BF) | (~sc1 & ~sc0 & L[3] & ~L[2] & ~L[1] & ~L[0] & BF) |
                 (~sc1 & sc0 & L[3] & ~L[2] & ~L[1] & ~L[0] & ~BF) | (~sc2 & ~sc1 & ~L[3] & ~L[2] & L[1] & ~L[0] & BF);

FlipF3  t2(clk, reset, EN, sf_c, s_c);
assign CT0 = (sc2 & ~sc1 & sc0);
assign SA = {sc2, sc1, sc0};
endmodule

//modulo del taller
module taller (input wire reset, clk, EN, input wire [3:0]T, input wire BF1, output wire CT1, output wire [2:0]SA1);
wire st0, st1, st2;
wire [2:0]s_t;
wire [2:0]sf_t;
assign st2 = s_t[2];
assign st1 = s_t[1];
assign st0 = s_t[0];
assign sf_t[2] = (st2 & ~st1 & ~T[3] & ~T[2] & ~T[1] & T[0]) | (st2 & ~st0 & ~T[3] & ~T[2] & ~T[1] & T[0]) | (st2 & ~T[3] & ~T[2] & ~T[1] & T[0] & ~BF1) | (st2 & ~st1 & ~st0 & ~T[3] & T[2] & ~T[1] & ~T[0]) |
                 (st2 & ~st1 & st0 & T[3] & ~T[2] & ~T[1] & ~T[0]) | (st2 & st1 & ~st0 & T[3] & ~T[2] & ~T[1] & ~T[0]) | (~st1 & ~st0 & ~T[3] & T[2] & ~T[1] & ~T[0] & BF1) |
                 (~st2 & st1 & st0 & ~T[3] & ~T[2] & ~T[1] & T[0] & BF1) | (~st2 & st1 & st0 & ~T[3] & ~T[2] & T[1] & ~T[0] & BF1) | (~st2 & ~st1 & ~st0 & T[3] & ~T[2] & ~T[1] & ~T[0] & BF1) | (st2 & st1 & st0 & ~T[3] & ~T[2] & T[1] & ~T[0] & ~BF1) |
                 (st2 & st1 & st0 & ~T[3] & T[2] & ~T[1] & ~T[0] & ~BF1) | (st2 & st0 & T[3] & ~T[2] & ~T[1] & ~T[0] & ~BF1);

assign sf_t[1] = (st1 & ~st0 & ~T[3] & ~T[2] & ~T[1] & T[0]) | (~st2 & st1 & ~T[3] & ~T[2] & T[1] & ~T[0]) | (st1 & ~T[3] & ~T[2] & ~T[1] & T[0] & ~BF1) | (st2 & st1 & ~st0 & T[3] & ~T[2] & ~T[1] & ~T[0]) |
                 (~st1 & st0 & ~T[3] & ~T[2] & ~T[1] & T[0] & BF1) | (~st2 & st0 & ~T[3] & ~T[2] & T[1] & ~T[0] & BF1) | (st1 & st0 & ~T[3] & ~T[2] & T[1] & ~T[0] & ~BF1) | (st2 & st1 & T[3] & ~T[2] & ~T[1] & ~T[0] & ~BF1) |
                 (st2 & ~st1 & ~st0 & ~T[3] & T[2] & ~T[1] & ~T[0] & BF1) | (st2 & ~st1 & st0 & T[3] & ~T[2] & ~T[1] & ~T[0] & BF1) |
                 (st2 & st1 & st0 & ~T[3] & T[2] & ~T[1] & ~T[0] & ~BF1);

assign sf_t[0] = (~st0 & ~T[3] & ~T[2] & ~T[1] & T[0] & BF1) | (st0 & ~T[3] & ~T[2] & ~T[1] & T[0] & ~BF1) | (~st2 & ~st0 & ~T[3] & ~T[2] & T[1] & ~T[0] & BF1) | (~st2 & st0 & ~T[3] & ~T[2] & T[1] & ~T[0] & ~BF1) |
                 (st1 & st0 & ~T[3] & ~T[2] & T[1] & ~T[0] & ~BF1) | (st2 & st0 & T[3] & ~T[2] & ~T[1] & ~T[0] & ~BF1) | (st2 & ~st1 & ~st0 & ~T[3] & T[2] & ~T[1] & ~T[0] & BF1) | (st2 & st1 & ~st0 & T[3] & ~T[2] & ~T[1] & ~T[0] & BF1) |
                 (~st2 & ~st1 & ~st0 & T[3] & ~T[2] & ~T[1] & ~T[0] & BF1) | (st2 & st1 & st0 & ~T[3] & T[2] & ~T[1] & ~T[0] & ~BF1) | (~st2 & st1 & ~T[3] & ~T[2] & T[1] & ~T[0] & BF1);

FlipF3 t3(clk, reset, EN, sf_t, s_t);
assign CT1 = (st2 & st1 & st0);
assign SA1 = {st2, st1, st0};
endmodule

//modulo donde se unen todas las fsm
module megafsm (input wire reset, clk, PB1, PB2, BF, BF1, input wire [3:0]T, input wire[3:0]C, output wire CT, CT1, output wire [2:0]SA, output wire [2:0]SA1);

wire C1, C2, T1, T2, E, E1;

antireb a1(clk, reset, PB1, C1);
antireb a2(clk, reset, PB2, T1);
antireb a3(clk, reset, BF, C2);
antireb a4(clk, reset, BF1, T2);


selector  m1(reset, clk, C1, T1, E, E1);
carwash   m2(reset, clk, E, C, C2, CT, SA);
taller    m3(reset, clk, E1, T, T2, CT1, SA1);

endmodule

PROYECTO/PROYECTO_tb.v
module testbench();

reg clk, reset;

reg PB1, PB2; //entradas selector
reg [3:0]T; //input taller
reg [3:0]C; //input car wash
reg BF, BF1; //push buttons
wire CT, CT1;
wire [2:0]SA;
wire [2:0]SA1; //salidas

megafsm  u1 (reset, clk, PB1, PB2, BF, BF1, T, C,  CT, CT1, SA, SA1);

always
#2 clk  <= ~clk;

initial begin
$display(" Selector ");
$display (" RST CLK PB1 PB2 BF BF1 T C | SA SA1 CT CT1");
$display("-----------------------------|------------");
$monitor("%b %b %b %b %b %b %b %b   |  %b %b %b %b", reset, clk, PB1, PB2, BF, BF1, T, C, SA, SA1, CT, CT1);
    reset = 0; clk = 1;
    #4 reset = 1; PB1 = 0; PB2 = 0; BF = 0; BF1 = 0; T[3] = 0; T[2] = 0; T[1] = 0; T[0] = 0; C[3] = 0; C[2] = 0; C[1] = 0; C[0] = 0;
    #1 reset = 0;
    #1 PB1 = 1;
    #4 PB1 = 0; C[3] = 1;
    #4 BF = 1;
    #4 BF = 0;
    #4 BF = 1;
    #4 BF = 0;
    #4 BF = 1;
    #4 BF = 0;
    #4 BF = 1;
    #4 BF = 0;
    #4 BF = 1;
    #4 BF = 0;
    #4 BF = 1;
    #4 BF = 0;
    #4 reset = 1; PB1 = 0; PB2 = 0; BF = 0; BF1 = 0; T[3] = 0; T[2] = 0; T[1] = 0; T[0] = 0; C[3] = 0; C[2] = 0; C[1] = 0; C[0] = 0;
    #1 reset = 0;
    #1 PB2 = 1;
    #4 PB2 = 0; T[0] = 1;
    #4 BF1 = 1;
    #4 BF1 = 0;
    #4 BF1 = 1;
    #4 BF1 = 0;
    #4 BF1 = 1;
    #4 BF1 = 0;
    #4 BF1 = 1;
    #4 BF1 = 0;
    #4 BF1 = 1;
    #4 BF1 = 0;
    #4 BF1 = 1;
    #4 BF1 = 0;
    #4 BF1 = 1;
    #4 BF1 = 0;
    #4 BF1 = 1;
    #4 BF1 = 0;





  end

  initial
    #145 $finish;

  initial begin
    $dumpfile("PROYECTO_tb.vcd");
    $dumpvars(0, testbench);

  end
  endmodule

PROYECTO/PROYECTO_tb.vcd
$date
	Sat Oct 17 23:03:52 2020
$end
$version
	Icarus Verilog
$end
$timescale
	1ps
$end
$scope module testbench $end
$var wire 3 ! SA1 [2:0] $end
$var wire 3 " SA [2:0] $end
$var wire 1 # CT1 $end
$var wire 1 $ CT $end
$var reg 1 % BF $end
$var reg 1 & BF1 $end
$var reg 4 ' C [3:0] $end
$var reg 1 ( PB1 $end
$var reg 1 ) PB2 $end
$var reg 4 * T [3:0] $end
$var reg 1 + clk $end
$var reg 1 , reset $end
$scope module u1 $end
$var wire 1 % BF $end
$var wire 1 & BF1 $end
$var wire 4 - C [3:0] $end
$var wire 1 ( PB1 $end
$var wire 1 ) PB2 $end
$var wire 4 . T [3:0] $end
$var wire 1 + clk $end
$var wire 1 , reset $end
$var wire 1 / T2 $end
$var wire 1 0 T1 $end
$var wire 3 1 SA1 [2:0] $end
$var wire 3 2 SA [2:0] $end
$var wire 1 3 E1 $end
$var wire 1 4 E $end
$var wire 1 # CT1 $end
$var wire 1 $ CT $end
$var wire 1 5 C2 $end
$var wire 1 6 C1 $end
$scope module a1 $end
$var wire 1 ( PB $end
$var wire 1 6 Q $end
$var wire 1 7 Y2 $end
$var wire 1 + clk $end
$var wire 1 , reset $end
$var wire 1 8 Y1 $end
$scope module F1 $end
$var wire 1 7 D $end
$var wire 1 9 E $end
$var wire 1 + clk $end
$var wire 1 , reset $end
$var reg 1 8 Q $end
$upscope $end
$upscope $end
$scope module a2 $end
$var wire 1 ) PB $end
$var wire 1 0 Q $end
$var wire 1 : Y2 $end
$var wire 1 + clk $end
$var wire 1 , reset $end
$var wire 1 ; Y1 $end
$scope module F1 $end
$var wire 1 : D $end
$var wire 1 < E $end
$var wire 1 + clk $end
$var wire 1 , reset $end
$var reg 1 ; Q $end
$upscope $end
$upscope $end
$scope module a3 $end
$var wire 1 % PB $end
$var wire 1 5 Q $end
$var wire 1 = Y2 $end
$var wire 1 + clk $end
$var wire 1 , reset $end
$var wire 1 > Y1 $end
$scope module F1 $end
$var wire 1 = D $end
$var wire 1 ? E $end
$var wire 1 + clk $end
$var wire 1 , reset $end
$var reg 1 > Q $end
$upscope $end
$upscope $end
$scope module a4 $end
$var wire 1 & PB $end
$var wire 1 / Q $end
$var wire 1 @ Y2 $end
$var wire 1 + clk $end
$var wire 1 , reset $end
$var wire 1 A Y1 $end
$scope module F1 $end
$var wire 1 @ D $end
$var wire 1 B E $end
$var wire 1 + clk $end
$var wire 1 , reset $end
$var reg 1 A Q $end
$upscope $end
$upscope $end
$scope module m1 $end
$var wire 1 4 E $end
$var wire 1 3 E1 $end
$var wire 1 6 PB1 $end
$var wire 1 0 PB2 $end
$var wire 1 + clk $end
$var wire 1 , reset $end
$var wire 2 C sf [1:0] $end
$var wire 1 D s1 $end
$var wire 1 E s0 $end
$var wire 2 F s [1:0] $end
$scope module t1 $end
$var wire 2 G D [1:0] $end
$var wire 1 H E $end
$var wire 1 + clk $end
$var wire 1 , reset $end
$var reg 2 I Q [1:0] $end
$upscope $end
$upscope $end
$scope module m2 $end
$var wire 1 5 BF $end
$var wire 1 $ CT0 $end
$var wire 1 4 EN $end
$var wire 4 J L [3:0] $end
$var wire 1 + clk $end
$var wire 1 , reset $end
$var wire 3 K sf_c [2:0] $end
$var wire 1 L sc2 $end
$var wire 1 M sc1 $end
$var wire 1 N sc0 $end
$var wire 3 O s_c [2:0] $end
$var wire 3 P SA [2:0] $end
$scope module t2 $end
$var wire 3 Q D [2:0] $end
$var wire 1 4 E $end
$var wire 1 + clk $end
$var wire 1 , reset $end
$var reg 3 R Q [2:0] $end
$upscope $end
$upscope $end
$scope module m3 $end
$var wire 1 / BF1 $end
$var wire 1 # CT1 $end
$var wire 1 3 EN $end
$var wire 4 S T [3:0] $end
$var wire 1 + clk $end
$var wire 1 , reset $end
$var wire 1 T st2 $end
$var wire 1 U st1 $end
$var wire 1 V st0 $end
$var wire 3 W sf_t [2:0] $end
$var wire 3 X s_t [2:0] $end
$var wire 3 Y SA1 [2:0] $end
$scope module t3 $end
$var wire 3 Z D [2:0] $end
$var wire 1 3 E $end
$var wire 1 + clk $end
$var wire 1 , reset $end
$var reg 3 [ Q [2:0] $end
$upscope $end
$upscope $end
$upscope $end
$upscope $end
$enddefinitions $end
#0
$dumpvars
bx [
bx Z
bx Y
bx X
bx W
xV
xU
xT
bx S
bx R
bx Q
bx P
bx O
xN
xM
xL
bx K
bx J
bx I
1H
bx G
bx F
xE
xD
bx C
1B
xA
x@
1?
x>
x=
1<
x;
x:
19
x8
x7
x6
x5
x4
x3
bx 2
bx 1
x0
x/
bx .
bx -
0,
1+
bx *
x)
x(
bx '
x&
x%
x$
x#
bx "
bx !
$end
#2
0+
#4
b0 C
b0 G
0#
0$
04
03
0V
0U
b0 !
b0 1
b0 Y
0T
0N
0M
b0 "
b0 2
b0 P
0L
0E
0D
b0 X
b0 [
b0 O
b0 R
b0 F
b0 I
0A
0>
0;
08
1+
b0 W
b0 Z
b0 K
b0 Q
0/
05
00
06
b0 '
b0 -
b0 J
b0 *
b0 .
b0 S
0@
0&
0=
0%
0:
0)
07
0(
1,
#5
0,
#6
0+
b1 C
b1 G
16
17
1(
#8
14
06
1E
b1 F
b1 I
18
1+
#10
0+
b1000 '
b1000 -
b1000 J
07
0(
#12
08
1+
#14
0+
b1 K
b1 Q
15
1=
1%
#16
05
b1 "
b1 2
b1 P
1N
b1 O
b1 R
1>
1+
#18
0+
0=
0%
#20
0>
1+
#22
0+
b10 K
b10 Q
15
1=
1%
#24
b10 K
b10 Q
05
0N
b10 "
b10 2
b10 P
1M
b10 O
b10 R
1>
1+
#26
0+
0=
0%
#28
0>
1+
#30
0+
b11 K
b11 Q
15
1=
1%
#32
b11 K
b11 Q
05
b11 "
b11 2
b11 P
1N
b11 O
b11 R
1>
1+
#34
0+
0=
0%
#36
0>
1+
#38
0+
b100 K
b100 Q
15
1=
1%
#40
b100 K
b100 Q
05
0N
0M
b100 "
b100 2
b100 P
1L
b100 O
b100 R
1>
1+
#42
0+
0=
0%
#44
0>
1+
#46
0+
b101 K
b101 Q
15
1=
1%
#48
b101 K
b101 Q
1$
05
b101 "
b101 2
b101 P
1N
b101 O
b101 R
1>
1+
#50
0+
0=
0%
#52
0>
1+
#54
0+
b0 K
b0 Q
15
1=
1%
#56
b0 K
b0 Q
0$
05
0N
b0 "
b0 2
b0 P
0L
b0 O
b0 R
1>
1+
#58
0+
0=
0%
#60
0>
1+
#62
b0 C
b0 G
04
0E
b0 F
b0 I
0+
b0 '
b0 -
b0 J
1,
#63
0,
#64
13
1D
1;
b10 F
b10 I
1+
b10 C
b10 G
00
1:
1)
#66
0+
#68
0;
1+
b1 *
b1 .
b1 S
0:
0)
#70
0+
#72
b1 !
b1 1
b1 Y
1V
1A
b1 X
b1 [
1+
b1 W
b1 Z
0/
1@
1&
#74
0+
#76
0A
1+
0@
0&
#78
0+
#80
0V
b10 !
b10 1
b10 Y
1U
1A
b10 X
b10 [
1+
b10 W
b10 Z
0/
1@
1&
#82
0+
#84
0A
1+
0@
0&
#86
0+
#88
b11 !
b11 1
b11 Y
1V
1A
b11 X
b11 [
1+
b11 W
b11 Z
0/
1@
1&
#90
0+
#92
0A
1+
0@
0&
#94
0+
#96
0V
0U
b100 !
b100 1
b100 Y
1T
1A
b100 X
b100 [
1+
b100 W
b100 Z
0/
1@
1&
#98
0+
#100
0A
1+
0@
0&
#102
0+
#104
b101 !
b101 1
b101 Y
1V
1A
b101 X
b101 [
1+
b101 W
b101 Z
0/
1@
1&
#106
0+
#108
0A
1+
0@
0&
#110
0+
#112
0V
b110 !
b110 1
b110 Y
1U
1A
b110 X
b110 [
1+
b110 W
b110 Z
0/
1@
1&
#114
0+
#116
0A
1+
0@
0&
#118
0+
#120
1#
b111 !
b111 1
b111 Y
1V
1A
b111 X
b111 [
1+
b111 W
b111 Z
0/
1@
1&
#122
0+
#124
0A
1+
0@
0&
#126
0+
#128
0#
0V
0U
b0 !
b0 1
b0 Y
0T
1A
b0 X
b0 [
1+
b0 W
b0 Z
0/
1@
1&
#130
0+
#132
0A
1+
0@
0&
